[
    {
      "name": "Davvisámegiella",
      "locale": "se",
      "return": "linnjá­molsun",
      "space": "gaska",
      "longPress": {
        "A": [
          "Ä",
          "Á",
          "À",
          "Â",
          "Ã",
          "Ā",
          "Ạ",
          "Å",
          "Æ"
        ],
        "Á": [
          "Q"
        ],
        "E": [
          "Ë",
          "É",
          "È",
          "Ê",
          "Ẽ",
          "Ē",
          "Ẹ",
          "Ė",
          "Ǝ"
        ],
        "I": [
          "Ï",
          "Í",
          "Ì",
          "Î",
          "Ĩ",
          "Ī",
          "Ị",
          "I"
        ],
        "O": [
          "Ø",
          "Ö",
          "Ó",
          "Ò",
          "Ô",
          "Õ",
          "Ō",
          "Ọ",
          "Ȯ",
          "Ő",
          "Œ"
        ],
        "U": [
          "Ü",
          "Ú",
          "Ù",
          "Û",
          "Ũ",
          "Ū",
          "Ụ",
          "Ů"
        ],
        "Y": [
          "Ÿ",
          "Ý",
          "Ỳ",
          "Ŷ",
          "Ỹ",
          "Ȳ",
          "Ẏ",
          "Y̊",
          "Ɏ"
        ],
        "Æ": [
          "Ä"
        ],
        "Ö": [
          "Ø"
        ],
        "C": [
          "Č",
          "Ç",
          "Ĉ"
        ],
        "Č": [
          "X"
        ],
        "G": [
          "Ǥ",
          "Ǧ",
          "Ģ"
        ],
        "K": [
          "Ǩ",
          "Ḵ",
          "Ķ"
        ],
        "N": [
          "Ŋ",
          "Ñ",
          "Ň",
          "Ṋ",
          "Ṉ"
        ],
        "S": [
          "Š",
          "Ŝ",
          "Ṣ",
          "Ș",
          "SS"
        ],
        "Š": [
          "W"
        ],
        "T": [
          "Ŧ",
          "Ț",
          "Ṱ",
          "Ṯ"
        ],
        "Z": [
          "Ž",
          "Ʒ",
          "Ǯ"
        ],
        "a": [
          "ä",
          "á",
          "à",
          "â",
          "ã",
          "ā",
          "ạ",
          "å",
          "æ"
        ],
        "á": [
          "q"
        ],
        "e": [
          "ë",
          "é",
          "è",
          "ê",
          "ẽ",
          "ē",
          "ẹ",
          "ė",
          "ǝ"
        ],
        "i": [
          "ï",
          "í",
          "ì",
          "î",
          "ĩ",
          "ī",
          "ị",
          "i"
        ],
        "o": [
          "ø",
          "ö",
          "ó",
          "ò",
          "ô",
          "õ",
          "ō",
          "ọ",
          "ȯ",
          "ő",
          "œ"
        ],
        "u": [
          "ü",
          "ú",
          "ù",
          "û",
          "ũ",
          "ū",
          "ụ",
          "ů"
        ],
        "y": [
          "ÿ",
          "ý",
          "ỳ",
          "ŷ",
          "ỹ",
          "ȳ",
          "ẏ",
          "ẙ",
          "ɏ"
        ],
        "æ": [
          "ä"
        ],
        "ö": [
          "ø"
        ],
        "c": [
          "č",
          "ç",
          "ĉ"
        ],
        "č": [
          "x"
        ],
        "g": [
          "ǥ",
          "ǧ",
          "ģ"
        ],
        "k": [
          "ǩ",
          "ḵ",
          "ķ"
        ],
        "n": [
          "ŋ",
          "ñ",
          "ň",
          "ṋ",
          "ṉ"
        ],
        "s": [
          "š",
          "ŝ",
          "ṣ",
          "ș",
          "ss"
        ],
        "š": [
          "w"
        ],
        "t": [
          "ŧ",
          "ț",
          "ṱ",
          "ṯ"
        ],
        "z": [
          "ž",
          "ʒ",
          "ǯ"
        ],
        "%": [
          "‰",
          "∞"
        ],
        "=": [
          "≠",
          "≈"
        ],
        "-": [
          "•",
          "–",
          "—"
        ],
        "&": [
          "§"
        ],
        "?": [
          "¿"
        ],
        "!": [
          "¡"
        ],
        ".": [
          ",",
          ";",
          ":",
          "?",
          "!",
          "¿",
          "¡"
        ],
        "\"": [
          "„",
          "“",
          "”",
          "«",
          "»"
        ],
        "'": [
          "‚",
          "‘",
          "’"
        ]
      },
      "deadKeys": {
        "iphone": {},
        "ipad-9in": {},
        "ipad-12in": {}
      },
      "transforms": null,
      "iphone": {
        "normal": [
          [
            "á",
            "š",
            "e",
            "r",
            "t",
            "y",
            "u",
            "i",
            "o",
            "p",
            "ŋ"
          ],
          [
            "a",
            "s",
            "d",
            "f",
            "g",
            "h",
            "j",
            "k",
            "l",
            "đ",
            "ŧ"
          ],
          [
            {
              "id": "_shift",
              "width": 1.25
            },
            {
              "id": "_spacer",
              "width": 0.25
            },
            "ž",
            "z",
            "č",
            "c",
            "v",
            "b",
            "n",
            "m",
            {
              "id": "_spacer",
              "width": 0.25
            },
            {
              "id": "_backspace",
              "width": 1.25
            }
          ]
        ],
        "shifted": [
          [
            "Á",
            "Š",
            "E",
            "R",
            "T",
            "Y",
            "U",
            "I",
            "O",
            "P",
            "Ŋ"
          ],
          [
            "A",
            "S",
            "D",
            "F",
            "G",
            "H",
            "J",
            "K",
            "L",
            "Đ",
            "Ŧ"
          ],
          [
            {
              "id": "_shift",
              "width": 1.25
            },
            {
              "id": "_spacer",
              "width": 0.25
            },
            "Ž",
            "Z",
            "Č",
            "C",
            "V",
            "B",
            "N",
            "M",
            {
              "id": "_spacer",
              "width": 0.25
            },
            {
              "id": "_backspace",
              "width": 1.25
            }
          ]
        ],
        "symbols-1": [
          [
            "1",
            "2",
            "3",
            "4",
            "5",
            "6",
            "7",
            "8",
            "9",
            "0"
          ],
          [
            "-",
            "/",
            ":",
            ";",
            "(",
            ")",
            "kr",
            "&",
            "@",
            "\""
          ],
          [
            {
              "id": "_shiftSymbols",
              "width": 1.0
            },
            {
              "id": "_spacer",
              "width": 0.25
            },
            ".",
            ",",
            "?",
            "!",
            "'",
            {
              "id": "_spacer",
              "width": 0.25
            },
            {
              "id": "_backspace",
              "width": 1.0
            }
          ]
        ],
        "symbols-2": [
          [
            "[",
            "]",
            "{",
            "}",
            "#",
            "%",
            "^",
            "*",
            "+",
            "="
          ],
          [
            "_",
            "\\",
            "|",
            "~",
            "<",
            ">",
            "€",
            "$",
            "£",
            "•"
          ],
          [
            {
              "id": "_shiftSymbols",
              "width": 1.0
            },
            {
              "id": "_spacer",
              "width": 0.25
            },
            ".",
            ",",
            "?",
            "!",
            "'",
            {
              "id": "_spacer",
              "width": 0.25
            },
            {
              "id": "_backspace",
              "width": 1.0
            }
          ]
        ]
      },
      "ipad-9in": {
        "normal": [
          [
            {
              "id": "`",
              "width": 0.75
            },
            "á",
            "š",
            "e",
            "r",
            "t",
            "y",
            "u",
            "i",
            "o",
            "p",
            "ŋ",
            {
              "id": "_backspace",
              "width": 1.25
            }
          ],
          [
            {
              "id": "_shift",
              "width": 1.0
            },
            "a",
            "s",
            "d",
            "f",
            "g",
            "h",
            "j",
            "k",
            "l",
            "đ",
            "ŧ",
            {
              "id": "_shift",
              "width": 1.0
            }
          ],
          [
            {
              "id": "_spacer",
              "width": 0.5
            },
            "ž",
            "z",
            "č",
            "c",
            "v",
            "b",
            "n",
            "m",
            ",",
            ".",
            {
              "id": "_spacer",
              "width": 0.5
            },
            {
              "id": "_return",
              "width": 2.0
            }
          ]
        ],
        "shifted": [
          [
            {
              "id": "`",
              "width": 0.75
            },
            "Á",
            "Š",
            "E",
            "R",
            "T",
            "Y",
            "U",
            "I",
            "O",
            "P",
            "Ŋ",
            {
              "id": "_backspace",
              "width": 1.25
            }
          ],
          [
            {
              "id": "_shift",
              "width": 1.0
            },
            "A",
            "S",
            "D",
            "F",
            "G",
            "H",
            "J",
            "K",
            "L",
            "Đ",
            "Ŧ",
            {
              "id": "_shift",
              "width": 1.0
            }
          ],
          [
            {
              "id": "_spacer",
              "width": 0.5
            },
            "Ž",
            "Z",
            "Č",
            "C",
            "V",
            "B",
            "N",
            "M",
            ",",
            ".",
            {
              "id": "_spacer",
              "width": 0.5
            },
            {
              "id": "_return",
              "width": 2.0
            }
          ]
        ],
        "alt": [
          [
            {
              "id": "@",
              "width": 0.75
            },
            "1",
            "2",
            "3",
            "4",
            "5",
            "6",
            "7",
            "8",
            "9",
            "0",
            "å",
            {
              "id": "_backspace",
              "width": 1.25
            }
          ],
          [
            {
              "id": "_shift",
              "width": 1.0
            },
            "%",
            "#",
            "kr",
            "&",
            "*",
            "(",
            ")",
            "'",
            "\"",
            "ø",
            "æ",
            {
              "id": "_shift",
              "width": 1.0
            }
          ],
          [
            {
              "id": "_spacer",
              "width": 0.5
            },
            "q",
            "w",
            "x",
            "-",
            "=",
            "/",
            ";",
            ":",
            "!",
            "?",
            {
              "id": "_spacer",
              "width": 0.5
            },
            {
              "id": "_return",
              "width": 2.0
            }
          ]
        ],
        "alt+shift": [
          [
            {
              "id": "@",
              "width": 0.75
            },
            "1",
            "2",
            "3",
            "4",
            "5",
            "6",
            "7",
            "8",
            "9",
            "0",
            "Å",
            {
              "id": "_backspace",
              "width": 1.25
            }
          ],
          [
            {
              "id": "_shift",
              "width": 1.0
            },
            "%",
            "#",
            "kr",
            "&",
            "*",
            "(",
            ")",
            "'",
            "\"",
            "Ø",
            "Æ",
            {
              "id": "_shift",
              "width": 1.0
            }
          ],
          [
            {
              "id": "_spacer",
              "width": 0.5
            },
            "Q",
            "W",
            "X",
            "-",
            "=",
            "/",
            ";",
            ":",
            "!",
            "?",
            {
              "id": "_spacer",
              "width": 0.5
            },
            {
              "id": "_return",
              "width": 2.0
            }
          ]
        ],
        "symbols-1": [
          [
            {
              "id": "_spacer",
              "width": 0.75
            },
            "1",
            "2",
            "3",
            "4",
            "5",
            "6",
            "7",
            "8",
            "9",
            "0",
            "`",
            {
              "id": "_backspace",
              "width": 1.25
            }
          ],
          [
            {
              "id": "_shiftSymbols",
              "width": 1.0
            },
            "@",
            "#",
            "kr",
            "&",
            "*",
            "(",
            ")",
            "'",
            "\"",
            "+",
            "•",
            {
              "id": "_shiftSymbols",
              "width": 1.0
            }
          ],
          [
            {
              "id": "_spacer",
              "width": 1.5
            },
            "%",
            "_",
            "-",
            "=",
            "/",
            ";",
            ":",
            ",",
            ".",
            {
              "id": "_spacer",
              "width": 0.5
            },
            {
              "id": "_return",
              "width": 2.0
            }
          ]
        ],
        "symbols-2": [
          [
            {
              "id": "_spacer",
              "width": 0.75
            },
            "1",
            "2",
            "3",
            "4",
            "5",
            "6",
            "7",
            "8",
            "9",
            "0",
            "´",
            {
              "id": "_backspace",
              "width": 1.25
            }
          ],
          [
            {
              "id": "_shiftSymbols",
              "width": 1.0
            },
            "€",
            "$",
            "£",
            "^",
            "[",
            "]",
            "{",
            "}",
            "—",
            "°",
            "…",
            {
              "id": "_shiftSymbols",
              "width": 1.0
            }
          ],
          [
            {
              "id": "_spacer",
              "width": 1.5
            },
            "§",
            "|",
            "~",
            "≠",
            "\\",
            "<",
            ">",
            "!",
            "?",
            {
              "id": "_spacer",
              "width": 0.5
            },
            {
              "id": "_return",
              "width": 2.0
            }
          ]
        ]
      },
      "ipad-12in": {
        "normal": [
          [
            "'",
            "1",
            "2",
            "3",
            "4",
            "5",
            "6",
            "7",
            "8",
            "9",
            "0",
            "+",
            "´",
            {
              "id": "_backspace",
              "width": 1.5
            }
          ],
          [
            {
              "id": "_spacer",
              "width": 1.5
            },
            "á",
            "š",
            "e",
            "r",
            "t",
            "y",
            "u",
            "i",
            "o",
            "p",
            "å",
            "ŋ",
            "đ"
          ],
          [
            {
              "id": "_caps",
              "width": 1.75
            },
            "a",
            "s",
            "d",
            "f",
            "g",
            "h",
            "j",
            "k",
            "l",
            "ø",
            "æ",
            {
              "id": "_return",
              "width": 1.75
            }
          ],
          [
            {
              "id": "_shift",
              "width": 1.25
            },
            "ž",
            "z",
            "č",
            "c",
            "v",
            "b",
            "n",
            "m",
            ",",
            ".",
            "-",
            {
              "id": "_shift",
              "width": 2.25
            }
          ]
        ],
        "shifted": [
          [
            "§",
            "!",
            "\"",
            "#",
            "kr",
            "%",
            "&",
            "/",
            "(",
            ")",
            "=",
            "?",
            "`",
            {
              "id": "_backspace",
              "width": 1.5
            }
          ],
          [
            {
              "id": "_spacer",
              "width": 1.5
            },
            "Á",
            "Š",
            "E",
            "R",
            "T",
            "Y",
            "U",
            "I",
            "O",
            "P",
            "Å",
            "Ŋ",
            "Đ"
          ],
          [
            {
              "id": "_caps",
              "width": 1.75
            },
            "A",
            "S",
            "D",
            "F",
            "G",
            "H",
            "J",
            "K",
            "L",
            "Ø",
            "Æ",
            {
              "id": "_return",
              "width": 1.75
            }
          ],
          [
            {
              "id": "_shift",
              "width": 1.25
            },
            "Ž",
            "Z",
            "Č",
            "C",
            "V",
            "B",
            "N",
            "M",
            ";",
            ":",
            "_",
            {
              "id": "_shift",
              "width": 2.25
            }
          ]
        ],
        "alt": [
          [
            "§",
            "!",
            "\"",
            "#",
            "kr",
            "%",
            "&",
            "/",
            "(",
            ")",
            "=",
            "?",
            "`",
            {
              "id": "_backspace",
              "width": 1.5
            }
          ],
          [
            {
              "id": "_spacer",
              "width": 1.5
            },
            "q",
            "w",
            "e",
            "r",
            "t",
            "y",
            "u",
            "i",
            "o",
            "p",
            "å",
            "ŋ",
            "đ"
          ],
          [
            {
              "id": "_caps",
              "width": 1.75
            },
            "a",
            "s",
            "d",
            "f",
            "g",
            "h",
            "j",
            "k",
            "l",
            "ö",
            "ä",
            {
              "id": "_return",
              "width": 1.75
            }
          ],
          [
            {
              "id": "_shift",
              "width": 1.25
            },
            "<",
            "z",
            "x",
            "c",
            "v",
            "b",
            "n",
            "m",
            ";",
            ":",
            "_",
            {
              "id": "_shift",
              "width": 2.25
            }
          ]
        ],
        "alt+shift": [
          [
            "§",
            "!",
            "\"",
            "#",
            "kr",
            "%",
            "&",
            "/",
            "(",
            ")",
            "=",
            "?",
            "`",
            {
              "id": "_backspace",
              "width": 1.5
            }
          ],
          [
            {
              "id": "_spacer",
              "width": 1.5
            },
            "Q",
            "W",
            "E",
            "R",
            "T",
            "Y",
            "U",
            "I",
            "O",
            "P",
            "Å",
            "Ŋ",
            "Đ"
          ],
          [
            {
              "id": "_caps",
              "width": 1.75
            },
            "A",
            "S",
            "D",
            "F",
            "G",
            "H",
            "J",
            "K",
            "L",
            "Ö",
            "Ä",
            {
              "id": "_return",
              "width": 1.75
            }
          ],
          [
            {
              "id": "_shift",
              "width": 1.25
            },
            ">",
            "Z",
            "X",
            "C",
            "V",
            "B",
            "N",
            "M",
            ";",
            ":",
            "_",
            {
              "id": "_shift",
              "width": 2.25
            }
          ]
        ],
        "symbols-1": [
          [
            "`",
            "1",
            "2",
            "3",
            "4",
            "5",
            "6",
            "7",
            "8",
            "9",
            "0",
            "<",
            ">",
            {
              "id": "_backspace",
              "width": 1.5
            }
          ],
          [
            {
              "id": "_spacer",
              "width": 1.5
            },
            "[",
            "]",
            "{",
            "}",
            "#",
            "%",
            "^",
            "*",
            "+",
            "=",
            "\\",
            "|",
            "~"
          ],
          [
            {
              "id": "_spacer",
              "width": 1.75
            },
            "-",
            "/",
            ":",
            ";",
            "(",
            ")",
            "kr",
            "&",
            "@",
            "$",
            "£",
            {
              "id": "_return",
              "width": 1.75
            }
          ],
          [
            {
              "id": "_spacer",
              "width": 3.25
            },
            "…",
            ".",
            ",",
            "?",
            "!",
            "'",
            "\"",
            "_",
            "€",
            {
              "id": "_spacer",
              "width": 2.25
            }
          ]
        ],
        "symbols-2": []
      }
    },
]
